<?xml version="1.0" encoding="UTF-8"?>
<persistence version="2.1" xmlns="http://xmlns.jcp.org/xml/ns/persistence" xmlns:xsi="http://www.w3.org/2001/XMLSchema-instance" xsi:schemaLocation="http://xmlns.jcp.org/xml/ns/persistence http://xmlns.jcp.org/xml/ns/persistence/persistence_2_1.xsd">
  <persistence-unit name="nust.systems_WorkingCrud_war_1.0PU" transaction-type="RESOURCE_LOCAL">
    <provider>org.eclipse.persistence.jpa.PersistenceProvider</provider>
    <class>nust.systems.workingcrud.entities.NUSTUSDApplicantEmployment</class>
    <class>nust.systems.workingcrud.entities.NUSTUSDApplicantChoice</class>
    <class>nust.systems.workingcrud.entities.NUSTUSDApplicantEducation</class>
    <class>nust.systems.workingcrud.entities.NUSTUSDApplicantQualification</class>
    <class>nust.systems.workingcrud.entities.NUSTUSDProgrammeFeeDetail</class>
    <class>nust.systems.workingcrud.entities.NUSTUSDApplicantReferee</class>
    <class>nust.systems.workingcrud.entities.NUSTUSDCommentLine</class>
    <class>nust.systems.workingcrud.entities.NUSTUSDApplicantSelectionAidJourn</class>
    <class>nust.systems.workingcrud.entities.NUSTUSDApplicant</class>
    <exclude-unlisted-classes>false</exclude-unlisted-classes>
    <properties>
      <property name="javax.persistence.jdbc.url" value="jdbc:sqlserver://196.220.119.58:1433;databaseName=TEST_NUST2017"/>
      <property name="javax.persistence.jdbc.user" value="sa"/>
      <property name="javax.persistence.jdbc.driver" value="com.microsoft.sqlserver.jdbc.SQLServerDriver"/>
      <property name="javax.persistence.jdbc.password" value="Monday1@nust.ac.zw"/>
    </properties>
  </persistence-unit>
</persistence>
